imgextractor/main.py
imgextractor-0.1.1.dist-info/entry_points.txt
imgextractor-0.1.1.dist-info/WHEEL
imgextractor-0.1.1.dist-info/METADATA
imgextractor-0.1.1.dist-info/RECORD
